{
  "version": "7",
  "dialect": "sqlite",
  "entries": [
    {
      "idx": 0,
      "version": "6",
      "when": 1762328387993,
      "tag": "0000_loving_puff_adder",
      "breakpoints": true
    },
    {
      "idx": 1,
      "version": "6",
      "when": 1762330047192,
      "tag": "0001_clear_kat_farrell",
      "breakpoints": true
    },
    {
      "idx": 2,
      "version": "6",
      "when": 1762367018677,
      "tag": "0002_giant_mattie_franklin",
      "breakpoints": true
    },
    {
      "idx": 3,
      "version": "6",
      "when": 1762377093201,
      "tag": "0003_pink_silver_samurai",
      "breakpoints": true
    },
    {
      "idx": 4,
      "version": "6",
      "when": 1762466225706,
      "tag": "0004_pink_tinkerer",
      "breakpoints": true
    },
    {
      "idx": 5,
      "version": "6",
      "when": 1762493494836,
      "tag": "0005_late_big_bertha",
      "breakpoints": true
    }
  ]
}